<?xml version="1.0" encoding="UTF-8"?>
<DEFECTS>
  <DEFECT>
    <SFA>
      <FILEPATH>F:\code\3rdparty\gdal-3.1.0\gdal-3.1.0\gdal\frmts\srtmhgt\</FILEPATH>
      <FILENAME>srtmhgtdataset.cpp</FILENAME>
      <LINE>369</LINE>
      <COLUMN>6</COLUMN>
    </SFA>
    <DEFECTCODE>6053</DEFECTCODE>
    <DESCRIPTION>对“strncpy”的前一调用可能没有为字符串“latLonValueString”添加字符串零终止符。</DESCRIPTION>
    <FUNCTION>SRTMHGTDataset::Open</FUNCTION>
    <DECORATED>?Open@SRTMHGTDataset@@SAPEAVGDALDataset@@PEAVGDALOpenInfo@@@Z</DECORATED>
    <FUNCLINE>323</FUNCLINE>
    <PROBABILITY>1</PROBABILITY>
    <RANK>1</RANK>
    <CATEGORY>
      <RULECATEGORY>mspft</RULECATEGORY>
    </CATEGORY>
    <PATH>
      <SFA>
        <FILEPATH>F:\code\3rdparty\gdal-3.1.0\gdal-3.1.0\gdal\frmts\srtmhgt\</FILEPATH>
        <FILENAME>srtmhgtdataset.cpp</FILENAME>
        <LINE>325</LINE>
        <COLUMN>6</COLUMN>
      </SFA>
      <SFA>
        <FILEPATH>F:\code\3rdparty\gdal-3.1.0\gdal-3.1.0\gdal\frmts\srtmhgt\</FILEPATH>
        <FILENAME>srtmhgtdataset.cpp</FILENAME>
        <LINE>328</LINE>
        <COLUMN>12</COLUMN>
      </SFA>
      <SFA>
        <FILEPATH>F:\code\3rdparty\gdal-3.1.0\gdal-3.1.0\gdal\frmts\srtmhgt\</FILEPATH>
        <FILENAME>srtmhgtdataset.cpp</FILENAME>
        <LINE>329</LINE>
        <COLUMN>34</COLUMN>
      </SFA>
      <SFA>
        <FILEPATH>F:\code\3rdparty\gdal-3.1.0\gdal-3.1.0\gdal\frmts\srtmhgt\</FILEPATH>
        <FILENAME>srtmhgtdataset.cpp</FILENAME>
        <LINE>329</LINE>
        <COLUMN>12</COLUMN>
      </SFA>
      <SFA>
        <FILEPATH>F:\code\3rdparty\gdal-3.1.0\gdal-3.1.0\gdal\frmts\srtmhgt\</FILEPATH>
        <FILENAME>srtmhgtdataset.cpp</FILENAME>
        <LINE>331</LINE>
        <COLUMN>28</COLUMN>
      </SFA>
      <SFA>
        <FILEPATH>F:\code\3rdparty\gdal-3.1.0\gdal-3.1.0\gdal\frmts\srtmhgt\</FILEPATH>
        <FILENAME>srtmhgtdataset.cpp</FILENAME>
        <LINE>330</LINE>
        <COLUMN>41</COLUMN>
      </SFA>
      <SFA>
        <FILEPATH>F:\code\3rdparty\gdal-3.1.0\gdal-3.1.0\gdal\frmts\srtmhgt\</FILEPATH>
        <FILENAME>srtmhgtdataset.cpp</FILENAME>
        <LINE>349</LINE>
        <COLUMN>28</COLUMN>
      </SFA>
      <SFA>
        <FILEPATH>F:\code\3rdparty\gdal-3.1.0\gdal-3.1.0\gdal\frmts\srtmhgt\</FILEPATH>
        <FILENAME>srtmhgtdataset.cpp</FILENAME>
        <LINE>348</LINE>
        <COLUMN>41</COLUMN>
      </SFA>
      <SFA>
        <FILEPATH>F:\code\3rdparty\gdal-3.1.0\gdal-3.1.0\gdal\frmts\srtmhgt\</FILEPATH>
        <FILENAME>srtmhgtdataset.cpp</FILENAME>
        <LINE>366</LINE>
        <COLUMN>7</COLUMN>
      </SFA>
      <SFA>
        <FILEPATH>F:\code\3rdparty\gdal-3.1.0\gdal-3.1.0\gdal\frmts\srtmhgt\</FILEPATH>
        <FILENAME>srtmhgtdataset.cpp</FILENAME>
        <LINE>367</LINE>
        <COLUMN>8</COLUMN>
      </SFA>
      <SFA>
        <FILEPATH>F:\code\3rdparty\gdal-3.1.0\gdal-3.1.0\gdal\frmts\srtmhgt\</FILEPATH>
        <FILENAME>srtmhgtdataset.cpp</FILENAME>
        <LINE>368</LINE>
        <COLUMN>9</COLUMN>
        <KEYEVENT>
          <ID>1</ID>
          <KIND>声明</KIND>
          <IMPORTANCE>Essential</IMPORTANCE>
          <MESSAGE>“latLonValueString”是“strncpy”的输出，不能为其添加字符串零终止符</MESSAGE>
        </KEYEVENT>
      </SFA>
      <SFA>
        <FILEPATH>F:\code\3rdparty\gdal-3.1.0\gdal-3.1.0\gdal\frmts\srtmhgt\</FILEPATH>
        <FILENAME>srtmhgtdataset.cpp</FILENAME>
        <LINE>369</LINE>
        <COLUMN>6</COLUMN>
        <KEYEVENT>
          <ID>2</ID>
          <KIND>使用情况</KIND>
          <IMPORTANCE>Full</IMPORTANCE>
          <MESSAGE>“latLonValueString”是对“atoi”的输入(在 c:\program files (x86)\windows kits\10\include\10.0.18362.0\ucrt\stdlib.h:447 处声明)</MESSAGE>
        </KEYEVENT>
      </SFA>
      <SFA>
        <FILEPATH>F:\code\3rdparty\gdal-3.1.0\gdal-3.1.0\gdal\frmts\srtmhgt\</FILEPATH>
        <FILENAME>srtmhgtdataset.cpp</FILENAME>
        <LINE>369</LINE>
        <COLUMN>6</COLUMN>
        <KEYEVENT>
          <ID>3</ID>
          <KIND>使用情况</KIND>
          <IMPORTANCE>Essential</IMPORTANCE>
          <MESSAGE>“latLonValueString”必须由“atoi”上的 SAL 批注添加字符串零终止符</MESSAGE>
        </KEYEVENT>
      </SFA>
    </PATH>
  </DEFECT>
</DEFECTS>