<?xml version="1.0" encoding="UTF-8"?>
<DEFECTS>
  <DEFECT>
    <SFA>
      <FILEPATH>F:\code\3rdparty\gdal-3.1.0\gdal-3.1.0\gdal\ogr\ogrsf_frmts\wasp\</FILEPATH>
      <FILENAME>ogrwasplayer.cpp</FILENAME>
      <LINE>481</LINE>
      <COLUMN>40</COLUMN>
    </SFA>
    <DEFECTCODE>6011</DEFECTCODE>
    <DESCRIPTION>取消对 NULL 指针“poLine”的引用。</DESCRIPTION>
    <FUNCTION>OGRWAsPLayer::WriteRoughness</FUNCTION>
    <DECORATED>?WriteRoughness@OGRWAsPLayer@@AEAAHPEAVOGRPolygon@@AEBN@Z</DECORATED>
    <FUNCLINE>428</FUNCLINE>
    <PROBABILITY>1</PROBABILITY>
    <RANK>4</RANK>
    <CATEGORY>
      <RULECATEGORY>mspft</RULECATEGORY>
    </CATEGORY>
    <PATH>
      <SFA>
        <FILEPATH>F:\code\3rdparty\gdal-3.1.0\gdal-3.1.0\gdal\ogr\ogrsf_frmts\wasp\</FILEPATH>
        <FILENAME>ogrwasplayer.cpp</FILENAME>
        <LINE>436</LINE>
        <COLUMN>11</COLUMN>
      </SFA>
      <SFA>
        <FILEPATH>F:\code\3rdparty\gdal-3.1.0\gdal-3.1.0\gdal\ogr\ogrsf_frmts\wasp\</FILEPATH>
        <FILENAME>ogrwasplayer.cpp</FILENAME>
        <LINE>437</LINE>
        <COLUMN>16</COLUMN>
      </SFA>
      <SFA>
        <FILEPATH>F:\code\3rdparty\gdal-3.1.0\gdal-3.1.0\gdal\ogr\ogrsf_frmts\wasp\</FILEPATH>
        <FILENAME>ogrwasplayer.cpp</FILENAME>
        <LINE>438</LINE>
        <COLUMN>23</COLUMN>
      </SFA>
      <SFA>
        <FILEPATH>F:\code\3rdparty\gdal-3.1.0\gdal-3.1.0\gdal\ogr\ogrsf_frmts\wasp\</FILEPATH>
        <FILENAME>ogrwasplayer.cpp</FILENAME>
        <LINE>439</LINE>
        <COLUMN>17</COLUMN>
      </SFA>
      <SFA>
        <FILEPATH>F:\code\3rdparty\gdal-3.1.0\gdal-3.1.0\gdal\ogr\ogrsf_frmts\wasp\</FILEPATH>
        <FILENAME>ogrwasplayer.cpp</FILENAME>
        <LINE>439</LINE>
        <COLUMN>23</COLUMN>
      </SFA>
      <SFA>
        <FILEPATH>F:\code\3rdparty\gdal-3.1.0\gdal-3.1.0\gdal\ogr\ogrsf_frmts\wasp\</FILEPATH>
        <FILENAME>ogrwasplayer.cpp</FILENAME>
        <LINE>441</LINE>
        <COLUMN>19</COLUMN>
      </SFA>
      <SFA>
        <FILEPATH>F:\code\3rdparty\gdal-3.1.0\gdal-3.1.0\gdal\ogr\ogrsf_frmts\wasp\</FILEPATH>
        <FILENAME>ogrwasplayer.cpp</FILENAME>
        <LINE>442</LINE>
        <COLUMN>25</COLUMN>
      </SFA>
      <SFA>
        <FILEPATH>F:\code\3rdparty\gdal-3.1.0\gdal-3.1.0\gdal\ogr\ogrsf_frmts\wasp\</FILEPATH>
        <FILENAME>ogrwasplayer.cpp</FILENAME>
        <LINE>444</LINE>
        <COLUMN>24</COLUMN>
      </SFA>
      <SFA>
        <FILEPATH>F:\code\3rdparty\gdal-3.1.0\gdal-3.1.0\gdal\ogr\ogrsf_frmts\wasp\</FILEPATH>
        <FILENAME>ogrwasplayer.cpp</FILENAME>
        <LINE>445</LINE>
        <COLUMN>17</COLUMN>
      </SFA>
      <SFA>
        <FILEPATH>F:\code\3rdparty\gdal-3.1.0\gdal-3.1.0\gdal\ogr\ogrsf_frmts\wasp\</FILEPATH>
        <FILENAME>ogrwasplayer.cpp</FILENAME>
        <LINE>447</LINE>
        <COLUMN>55</COLUMN>
      </SFA>
      <SFA>
        <FILEPATH>F:\code\3rdparty\gdal-3.1.0\gdal-3.1.0\gdal\ogr\ogrsf_frmts\wasp\</FILEPATH>
        <FILENAME>ogrwasplayer.cpp</FILENAME>
        <LINE>456</LINE>
        <COLUMN>16</COLUMN>
      </SFA>
      <SFA>
        <FILEPATH>F:\code\3rdparty\gdal-3.1.0\gdal-3.1.0\gdal\ogr\ogrsf_frmts\wasp\</FILEPATH>
        <FILENAME>ogrwasplayer.cpp</FILENAME>
        <LINE>457</LINE>
        <COLUMN>16</COLUMN>
      </SFA>
      <SFA>
        <FILEPATH>F:\code\3rdparty\gdal-3.1.0\gdal-3.1.0\gdal\ogr\ogrsf_frmts\wasp\</FILEPATH>
        <FILENAME>ogrwasplayer.cpp</FILENAME>
        <LINE>460</LINE>
        <COLUMN>34</COLUMN>
      </SFA>
      <SFA>
        <FILEPATH>F:\code\3rdparty\gdal-3.1.0\gdal-3.1.0\gdal\ogr\ogrsf_frmts\wasp\</FILEPATH>
        <FILENAME>ogrwasplayer.cpp</FILENAME>
        <LINE>461</LINE>
        <COLUMN>29</COLUMN>
      </SFA>
      <SFA>
        <FILEPATH>F:\code\3rdparty\gdal-3.1.0\gdal-3.1.0\gdal\ogr\ogrsf_frmts\wasp\</FILEPATH>
        <FILENAME>ogrwasplayer.cpp</FILENAME>
        <LINE>462</LINE>
        <COLUMN>29</COLUMN>
      </SFA>
      <SFA>
        <FILEPATH>F:\code\3rdparty\gdal-3.1.0\gdal-3.1.0\gdal\ogr\ogrsf_frmts\wasp\</FILEPATH>
        <FILENAME>ogrwasplayer.cpp</FILENAME>
        <LINE>464</LINE>
        <COLUMN>20</COLUMN>
      </SFA>
      <SFA>
        <FILEPATH>F:\code\3rdparty\gdal-3.1.0\gdal-3.1.0\gdal\ogr\ogrsf_frmts\wasp\</FILEPATH>
        <FILENAME>ogrwasplayer.cpp</FILENAME>
        <LINE>465</LINE>
        <COLUMN>45</COLUMN>
      </SFA>
      <SFA>
        <FILEPATH>F:\code\3rdparty\gdal-3.1.0\gdal-3.1.0\gdal\ogr\ogrsf_frmts\wasp\</FILEPATH>
        <FILENAME>ogrwasplayer.cpp</FILENAME>
        <LINE>467</LINE>
        <COLUMN>35</COLUMN>
      </SFA>
      <SFA>
        <FILEPATH>F:\code\3rdparty\gdal-3.1.0\gdal-3.1.0\gdal\ogr\ogrsf_frmts\wasp\</FILEPATH>
        <FILENAME>ogrwasplayer.cpp</FILENAME>
        <LINE>469</LINE>
        <COLUMN>35</COLUMN>
      </SFA>
      <SFA>
        <FILEPATH>F:\code\3rdparty\gdal-3.1.0\gdal-3.1.0\gdal\ogr\ogrsf_frmts\wasp\</FILEPATH>
        <FILENAME>ogrwasplayer.cpp</FILENAME>
        <LINE>481</LINE>
        <COLUMN>40</COLUMN>
      </SFA>
      <SFA>
        <FILEPATH>F:\code\3rdparty\gdal-3.1.0\gdal-3.1.0\gdal\ogr\ogrsf_frmts\wasp\</FILEPATH>
        <FILENAME>ogrwasplayer.cpp</FILENAME>
        <LINE>464</LINE>
        <COLUMN>20</COLUMN>
      </SFA>
      <SFA>
        <FILEPATH>F:\code\3rdparty\gdal-3.1.0\gdal-3.1.0\gdal\ogr\ogrsf_frmts\wasp\</FILEPATH>
        <FILENAME>ogrwasplayer.cpp</FILENAME>
        <LINE>465</LINE>
        <COLUMN>45</COLUMN>
      </SFA>
      <SFA>
        <FILEPATH>F:\code\3rdparty\gdal-3.1.0\gdal-3.1.0\gdal\ogr\ogrsf_frmts\wasp\</FILEPATH>
        <FILENAME>ogrwasplayer.cpp</FILENAME>
        <LINE>467</LINE>
        <COLUMN>35</COLUMN>
      </SFA>
      <SFA>
        <FILEPATH>F:\code\3rdparty\gdal-3.1.0\gdal-3.1.0\gdal\ogr\ogrsf_frmts\wasp\</FILEPATH>
        <FILENAME>ogrwasplayer.cpp</FILENAME>
        <LINE>469</LINE>
        <COLUMN>35</COLUMN>
        <KEYEVENT>
          <ID>1</ID>
          <KIND>声明</KIND>
          <IMPORTANCE>Essential</IMPORTANCE>
          <MESSAGE>“poLine”可能为 NULL</MESSAGE>
        </KEYEVENT>
      </SFA>
      <SFA>
        <FILEPATH>F:\code\3rdparty\gdal-3.1.0\gdal-3.1.0\gdal\ogr\ogrsf_frmts\wasp\</FILEPATH>
        <FILENAME>ogrwasplayer.cpp</FILENAME>
        <LINE>481</LINE>
        <COLUMN>40</COLUMN>
        <KEYEVENT>
          <ID>2</ID>
          <KIND>使用情况</KIND>
          <IMPORTANCE>Essential</IMPORTANCE>
          <MESSAGE>已取消对“poLine”的引用，但可能仍为 NULL</MESSAGE>
        </KEYEVENT>
      </SFA>
    </PATH>
  </DEFECT>
</DEFECTS>